{"phase":66,"migration":"supabase/migrations/20260718163000_phase_66_commercial_release_versioning.sql","api":"app/api/v1/developments/[id]/commercial-releases/route.ts","page":"app/(crm)/developments/[id]/commercial-versions/page.tsx","simulation":"app/api/v1/leads/[id]/commercial-simulation/route.ts","sources":["priceTableMaterial","salesMirrorMaterialOrAppliedImport","paymentRule"],"statuses":["draft","active","superseded","expired","revoked"],"requires":["singleActiveRelease","projectSourceValidation","validityWindow","directorActivation","humanReason","atomicSupersede","materialAlignment","paymentRuleAlignment","simulationSnapshot","tenantIsolation","auditEvents","rls","noClientWrite"]}
